ionoscloud_dns/__init__.py
ionoscloud_dns/api_client.py
ionoscloud_dns/api_response.py
ionoscloud_dns/configuration.py
ionoscloud_dns/exceptions.py
ionoscloud_dns/rest.py
ionoscloud_dns/test-driver.py
ionoscloud_dns/api/__init__.py
ionoscloud_dns/api/dnssec_api.py
ionoscloud_dns/api/quota_api.py
ionoscloud_dns/api/records_api.py
ionoscloud_dns/api/reverse_records_api.py
ionoscloud_dns/api/secondary_zones_api.py
ionoscloud_dns/api/zone_files_api.py
ionoscloud_dns/api/zones_api.py
ionoscloud_dns/models/__init__.py
ionoscloud_dns/models/algorithm.py
ionoscloud_dns/models/common_zone.py
ionoscloud_dns/models/common_zone_read.py
ionoscloud_dns/models/common_zone_read_list.py
ionoscloud_dns/models/dnssec_key.py
ionoscloud_dns/models/dnssec_key_create.py
ionoscloud_dns/models/dnssec_key_parameters.py
ionoscloud_dns/models/dnssec_key_read_creation.py
ionoscloud_dns/models/dnssec_key_read_list.py
ionoscloud_dns/models/dnssec_key_read_list_metadata.py
ionoscloud_dns/models/dnssec_key_read_list_properties.py
ionoscloud_dns/models/dnssec_key_read_list_properties_key_parameters.py
ionoscloud_dns/models/dnssec_key_read_list_properties_nsec_parameters.py
ionoscloud_dns/models/error.py
ionoscloud_dns/models/error_messages.py
ionoscloud_dns/models/key_data.py
ionoscloud_dns/models/key_parameters.py
ionoscloud_dns/models/ksk_bits.py
ionoscloud_dns/models/links.py
ionoscloud_dns/models/metadata.py
ionoscloud_dns/models/metadata_for_secondary_zone_records.py
ionoscloud_dns/models/metadata_with_state_fqdn_zone_id.py
ionoscloud_dns/models/metadata_with_state_fqdn_zone_id_all_of.py
ionoscloud_dns/models/metadata_with_state_nameservers.py
ionoscloud_dns/models/metadata_with_state_nameservers_all_of.py
ionoscloud_dns/models/nsec_mode.py
ionoscloud_dns/models/nsec_parameters.py
ionoscloud_dns/models/provisioning_state.py
ionoscloud_dns/models/quota.py
ionoscloud_dns/models/quota_detail.py
ionoscloud_dns/models/record.py
ionoscloud_dns/models/record_create.py
ionoscloud_dns-1.3.0.dist-info/LICENSE
ionoscloud_dns-1.3.0.dist-info/METADATA
ionoscloud_dns-1.3.0.dist-info/WHEEL
ionoscloud_dns-1.3.0.dist-info/top_level.txt
ionoscloud_dns-1.3.0.dist-info/RECORD
